ease_recommender/__init__.py
ease_recommender/py.typed
ease_recommender-0.1.0.dist-info/LICENSE
ease_recommender-0.1.0.dist-info/METADATA
ease_recommender-0.1.0.dist-info/WHEEL
ease_recommender-0.1.0.dist-info/entry_points.txt
ease_recommender-0.1.0.dist-info/RECORD
